st_login_form/__init__.py
st_login_form-1.3.0.dist-info/licenses/LICENSE
st_login_form-1.3.0.dist-info/METADATA
st_login_form-1.3.0.dist-info/WHEEL
st_login_form-1.3.0.dist-info/top_level.txt
st_login_form-1.3.0.dist-info/RECORD
