Metadata-Version: 2.4
Name: st-login-form
Version: 1.3.0
Summary: A streamlit component that creates customizable user authentication forms connected to a Supabase DB. It lets users create a new username and password, login to an existing account, or login as an anonymous guest.
Home-page: https://github.com/SiddhantSadangi/st_login_form
Author: Siddhant Sadangi
Author-email: siddhant.sadangi@gmail.com
Project-URL: Documentation, https://github.com/SiddhantSadangi/st_login_form/blob/main/README.md
Project-URL: Funding, https://www.buymeacoffee.com/siddhantsadangi
Keywords: streamlit,login,authentication,supabase
Classifier: Environment :: Plugins
Classifier: Environment :: Web Environment
Classifier: Intended Audience :: Developers
Classifier: License :: OSI Approved :: MIT License
Classifier: Operating System :: OS Independent
Classifier: Programming Language :: Python
Classifier: Topic :: Software Development :: Libraries :: Python Modules
Classifier: Topic :: Security
Classifier: Topic :: Software Development :: User Interfaces
Requires-Python: >=3.9
License-File: LICENSE
Requires-Dist: streamlit>=1.2
Requires-Dist: jinja2>=3.1.6
Requires-Dist: st_supabase_connection>=2.0
Requires-Dist: argon2-cffi>=23.1.0
Dynamic: author
Dynamic: author-email
Dynamic: classifier
Dynamic: description
Dynamic: description-content-type
Dynamic: home-page
Dynamic: keywords
Dynamic: license-file
Dynamic: project-url
Dynamic: requires-dist
Dynamic: requires-python
Dynamic: summary
